cdk_cr_constructs/__init__.py
cdk_cr_constructs/py.typed
cdk_cr_constructs/_jsii/__init__.py
cdk_cr_constructs/_jsii/cdk-cr-constructs@2.1.679.jsii.tgz
cdk_cr_constructs-2.1.679.dist-info/LICENSE
cdk_cr_constructs-2.1.679.dist-info/METADATA
cdk_cr_constructs-2.1.679.dist-info/WHEEL
cdk_cr_constructs-2.1.679.dist-info/top_level.txt
cdk_cr_constructs-2.1.679.dist-info/RECORD
